{
    "os": "Linux-6.5.0-44-generic-x86_64-with-glibc2.35",
    "python": "3.9.18",
    "heartbeatAt": "2024-08-15T07:13:33.256339",
    "startedAt": "2024-08-15T07:13:32.601558",
    "docker": null,
    "cuda": null,
    "args": [
        "--use_wandb",
        "--group_name",
        "self_play"
    ],
    "state": "running",
    "program": "/home/uosai/Desktop/marl/onpolicy/train_grf.py",
    "codePathLocal": "train_grf.py",
    "codePath": "onpolicy/train_grf.py",
    "git": {
        "remote": "https://github.com/singforai/marl.git",
        "commit": "b29a31bd20fdf0bc2a244b08a6b532139bca42c3"
    },
    "email": "singfor7012@gmail.com",
    "root": "/home/uosai/Desktop/marl",
    "host": "uos-desktop",
    "username": "uosai",
    "executable": "/home/uosai/Desktop/miniconda3/envs/marl/bin/python",
    "cpu_count": 12,
    "cpu_count_logical": 24,
    "cpu_freq": {
        "current": 3253.238041666666,
        "min": 2200.0,
        "max": 3700.0
    },
    "cpu_freq_per_core": [
        {
            "current": 2918.82,
            "min": 2200.0,
            "max": 3700.0
        },
        {
            "current": 3118.161,
            "min": 2200.0,
            "max": 3700.0
        },
        {
            "current": 3111.628,
            "min": 2200.0,
            "max": 3700.0
        },
        {
            "current": 2200.0,
            "min": 2200.0,
            "max": 3700.0
        },
        {
            "current": 4425.861,
            "min": 2200.0,
            "max": 3700.0
        },
        {
            "current": 2200.0,
            "min": 2200.0,
            "max": 3700.0
        },
        {
            "current": 2200.0,
            "min": 2200.0,
            "max": 3700.0
        },
        {
            "current": 2200.0,
            "min": 2200.0,
            "max": 3700.0
        },
        {
            "current": 3742.516,
            "min": 2200.0,
            "max": 3700.0
        },
        {
            "current": 2200.0,
            "min": 2200.0,
            "max": 3700.0
        },
        {
            "current": 2200.0,
            "min": 2200.0,
            "max": 3700.0
        },
        {
            "current": 2404.747,
            "min": 2200.0,
            "max": 3700.0
        },
        {
            "current": 2930.511,
            "min": 2200.0,
            "max": 3700.0
        },
        {
            "current": 2918.728,
            "min": 2200.0,
            "max": 3700.0
        },
        {
            "current": 2877.399,
            "min": 2200.0,
            "max": 3700.0
        },
        {
            "current": 3609.18,
            "min": 2200.0,
            "max": 3700.0
        },
        {
            "current": 3992.051,
            "min": 2200.0,
            "max": 3700.0
        },
        {
            "current": 3702.18,
            "min": 2200.0,
            "max": 3700.0
        },
        {
            "current": 3481.686,
            "min": 2200.0,
            "max": 3700.0
        },
        {
            "current": 4493.856,
            "min": 2200.0,
            "max": 3700.0
        },
        {
            "current": 3755.785,
            "min": 2200.0,
            "max": 3700.0
        },
        {
            "current": 4109.322,
            "min": 2200.0,
            "max": 3700.0
        },
        {
            "current": 2200.0,
            "min": 2200.0,
            "max": 3700.0
        },
        {
            "current": 2460.571,
            "min": 2200.0,
            "max": 3700.0
        }
    ],
    "disk": {
        "/": {
            "total": 233.17998886108398,
            "used": 190.73432159423828
        }
    },
    "gpu": "NVIDIA GeForce RTX 3080",
    "gpu_count": 2,
    "gpu_devices": [
        {
            "name": "NVIDIA GeForce RTX 3080",
            "memory_total": 10737418240
        },
        {
            "name": "NVIDIA GeForce RTX 3080",
            "memory_total": 10737418240
        }
    ],
    "memory": {
        "total": 62.709049224853516
    }
}
