{
    "os": "Linux-5.4.0-125-generic-x86_64-with-glibc2.31",
    "python": "3.9.19",
    "heartbeatAt": "2024-07-16T10:14:45.779247",
    "startedAt": "2024-07-16T10:14:45.120607",
    "docker": null,
    "cuda": null,
    "args": [
        "--seed",
        "4",
        "--experiment_name",
        "XT_TiZero",
        "--group_name",
        "XT_TiZero",
        "--algorithm_name",
        "tizero",
        "--use_wandb",
        "--n_rollout_threads",
        "10",
        "--use_xt",
        "--num_gpu",
        "3"
    ],
    "state": "running",
    "program": "/root/marl/onpolicy/train_grf.py",
    "codePathLocal": "train_grf.py",
    "codePath": "onpolicy/train_grf.py",
    "git": {
        "remote": "https://github.com/singforai/marl.git",
        "commit": "e3e73c0f9f57a7e997a8b884537e0b6de507f9da"
    },
    "email": "singfor7012@gmail.com",
    "root": "/root/marl",
    "host": "cc6d4f284c5a",
    "username": "root",
    "executable": "/root/miniconda3/envs/marl/bin/python",
    "cpu_count": 128,
    "cpu_count_logical": 128,
    "cpu_freq": {
        "current": 2749.048453124999,
        "min": 1500.0,
        "max": 2450.0
    },
    "cpu_freq_per_core": [
        {
            "current": 2599.622,
            "min": 1500.0,
            "max": 2450.0
        },
        {
            "current": 2597.583,
            "min": 1500.0,
            "max": 2450.0
        },
        {
            "current": 2592.388,
            "min": 1500.0,
            "max": 2450.0
        },
        {
            "current": 2589.137,
            "min": 1500.0,
            "max": 2450.0
        },
        {
            "current": 2594.386,
            "min": 1500.0,
            "max": 2450.0
        },
        {
            "current": 2615.81,
            "min": 1500.0,
            "max": 2450.0
        },
        {
            "current": 3249.746,
            "min": 1500.0,
            "max": 2450.0
        },
        {
            "current": 2596.647,
            "min": 1500.0,
            "max": 2450.0
        },
        {
            "current": 3249.676,
            "min": 1500.0,
            "max": 2450.0
        },
        {
            "current": 2600.076,
            "min": 1500.0,
            "max": 2450.0
        },
        {
            "current": 2599.784,
            "min": 1500.0,
            "max": 2450.0
        },
        {
            "current": 2599.805,
            "min": 1500.0,
            "max": 2450.0
        },
        {
            "current": 2599.26,
            "min": 1500.0,
            "max": 2450.0
        },
        {
            "current": 2597.313,
            "min": 1500.0,
            "max": 2450.0
        },
        {
            "current": 2599.447,
            "min": 1500.0,
            "max": 2450.0
        },
        {
            "current": 2596.456,
            "min": 1500.0,
            "max": 2450.0
        },
        {
            "current": 2594.577,
            "min": 1500.0,
            "max": 2450.0
        },
        {
            "current": 2596.307,
            "min": 1500.0,
            "max": 2450.0
        },
        {
            "current": 2593.063,
            "min": 1500.0,
            "max": 2450.0
        },
        {
            "current": 2593.817,
            "min": 1500.0,
            "max": 2450.0
        },
        {
            "current": 2596.355,
            "min": 1500.0,
            "max": 2450.0
        },
        {
            "current": 2596.139,
            "min": 1500.0,
            "max": 2450.0
        },
        {
            "current": 3249.527,
            "min": 1500.0,
            "max": 2450.0
        },
        {
            "current": 2593.789,
            "min": 1500.0,
            "max": 2450.0
        },
        {
            "current": 2620.227,
            "min": 1500.0,
            "max": 2450.0
        },
        {
            "current": 2597.718,
            "min": 1500.0,
            "max": 2450.0
        },
        {
            "current": 2596.377,
            "min": 1500.0,
            "max": 2450.0
        },
        {
            "current": 3249.196,
            "min": 1500.0,
            "max": 2450.0
        },
        {
            "current": 2599.174,
            "min": 1500.0,
            "max": 2450.0
        },
        {
            "current": 2597.55,
            "min": 1500.0,
            "max": 2450.0
        },
        {
            "current": 3249.902,
            "min": 1500.0,
            "max": 2450.0
        },
        {
            "current": 2598.568,
            "min": 1500.0,
            "max": 2450.0
        },
        {
            "current": 2599.242,
            "min": 1500.0,
            "max": 2450.0
        },
        {
            "current": 2598.389,
            "min": 1500.0,
            "max": 2450.0
        },
        {
            "current": 2599.68,
            "min": 1500.0,
            "max": 2450.0
        },
        {
            "current": 3249.533,
            "min": 1500.0,
            "max": 2450.0
        },
        {
            "current": 2598.138,
            "min": 1500.0,
            "max": 2450.0
        },
        {
            "current": 3249.424,
            "min": 1500.0,
            "max": 2450.0
        },
        {
            "current": 2593.115,
            "min": 1500.0,
            "max": 2450.0
        },
        {
            "current": 3249.366,
            "min": 1500.0,
            "max": 2450.0
        },
        {
            "current": 2574.342,
            "min": 1500.0,
            "max": 2450.0
        },
        {
            "current": 2599.973,
            "min": 1500.0,
            "max": 2450.0
        },
        {
            "current": 2597.53,
            "min": 1500.0,
            "max": 2450.0
        },
        {
            "current": 2596.59,
            "min": 1500.0,
            "max": 2450.0
        },
        {
            "current": 2596.872,
            "min": 1500.0,
            "max": 2450.0
        },
        {
            "current": 3248.945,
            "min": 1500.0,
            "max": 2450.0
        },
        {
            "current": 2599.452,
            "min": 1500.0,
            "max": 2450.0
        },
        {
            "current": 3250.088,
            "min": 1500.0,
            "max": 2450.0
        },
        {
            "current": 3250.095,
            "min": 1500.0,
            "max": 2450.0
        },
        {
            "current": 3249.714,
            "min": 1500.0,
            "max": 2450.0
        },
        {
            "current": 2597.518,
            "min": 1500.0,
            "max": 2450.0
        },
        {
            "current": 2595.073,
            "min": 1500.0,
            "max": 2450.0
        },
        {
            "current": 2599.39,
            "min": 1500.0,
            "max": 2450.0
        },
        {
            "current": 2596.132,
            "min": 1500.0,
            "max": 2450.0
        },
        {
            "current": 2598.769,
            "min": 1500.0,
            "max": 2450.0
        },
        {
            "current": 2596.657,
            "min": 1500.0,
            "max": 2450.0
        },
        {
            "current": 3250.081,
            "min": 1500.0,
            "max": 2450.0
        },
        {
            "current": 3250.073,
            "min": 1500.0,
            "max": 2450.0
        },
        {
            "current": 2598.87,
            "min": 1500.0,
            "max": 2450.0
        },
        {
            "current": 2594.03,
            "min": 1500.0,
            "max": 2450.0
        },
        {
            "current": 2597.958,
            "min": 1500.0,
            "max": 2450.0
        },
        {
            "current": 2599.601,
            "min": 1500.0,
            "max": 2450.0
        },
        {
            "current": 2599.794,
            "min": 1500.0,
            "max": 2450.0
        },
        {
            "current": 2595.002,
            "min": 1500.0,
            "max": 2450.0
        },
        {
            "current": 3249.035,
            "min": 1500.0,
            "max": 2450.0
        },
        {
            "current": 2595.742,
            "min": 1500.0,
            "max": 2450.0
        },
        {
            "current": 2600.001,
            "min": 1500.0,
            "max": 2450.0
        },
        {
            "current": 2596.876,
            "min": 1500.0,
            "max": 2450.0
        },
        {
            "current": 2598.985,
            "min": 1500.0,
            "max": 2450.0
        },
        {
            "current": 2596.697,
            "min": 1500.0,
            "max": 2450.0
        },
        {
            "current": 2599.167,
            "min": 1500.0,
            "max": 2450.0
        },
        {
            "current": 2597.664,
            "min": 1500.0,
            "max": 2450.0
        },
        {
            "current": 2598.434,
            "min": 1500.0,
            "max": 2450.0
        },
        {
            "current": 2599.403,
            "min": 1500.0,
            "max": 2450.0
        },
        {
            "current": 2593.32,
            "min": 1500.0,
            "max": 2450.0
        },
        {
            "current": 3249.955,
            "min": 1500.0,
            "max": 2450.0
        },
        {
            "current": 2595.79,
            "min": 1500.0,
            "max": 2450.0
        },
        {
            "current": 2596.621,
            "min": 1500.0,
            "max": 2450.0
        },
        {
            "current": 2595.834,
            "min": 1500.0,
            "max": 2450.0
        },
        {
            "current": 2599.726,
            "min": 1500.0,
            "max": 2450.0
        },
        {
            "current": 2596.108,
            "min": 1500.0,
            "max": 2450.0
        },
        {
            "current": 3249.893,
            "min": 1500.0,
            "max": 2450.0
        },
        {
            "current": 2596.876,
            "min": 1500.0,
            "max": 2450.0
        },
        {
            "current": 3249.735,
            "min": 1500.0,
            "max": 2450.0
        },
        {
            "current": 2596.416,
            "min": 1500.0,
            "max": 2450.0
        },
        {
            "current": 2599.217,
            "min": 1500.0,
            "max": 2450.0
        },
        {
            "current": 2596.298,
            "min": 1500.0,
            "max": 2450.0
        },
        {
            "current": 2595.679,
            "min": 1500.0,
            "max": 2450.0
        },
        {
            "current": 2598.496,
            "min": 1500.0,
            "max": 2450.0
        },
        {
            "current": 3248.62,
            "min": 1500.0,
            "max": 2450.0
        },
        {
            "current": 3058.132,
            "min": 1500.0,
            "max": 2450.0
        },
        {
            "current": 3249.073,
            "min": 1500.0,
            "max": 2450.0
        },
        {
            "current": 2600.259,
            "min": 1500.0,
            "max": 2450.0
        },
        {
            "current": 2596.471,
            "min": 1500.0,
            "max": 2450.0
        },
        {
            "current": 2598.634,
            "min": 1500.0,
            "max": 2450.0
        },
        {
            "current": 2599.867,
            "min": 1500.0,
            "max": 2450.0
        },
        {
            "current": 3250.071,
            "min": 1500.0,
            "max": 2450.0
        },
        {
            "current": 2596.266,
            "min": 1500.0,
            "max": 2450.0
        },
        {
            "current": 2598.144,
            "min": 1500.0,
            "max": 2450.0
        },
        {
            "current": 3249.957,
            "min": 1500.0,
            "max": 2450.0
        },
        {
            "current": 3249.561,
            "min": 1500.0,
            "max": 2450.0
        },
        {
            "current": 2594.962,
            "min": 1500.0,
            "max": 2450.0
        },
        {
            "current": 2594.219,
            "min": 1500.0,
            "max": 2450.0
        },
        {
            "current": 2598.812,
            "min": 1500.0,
            "max": 2450.0
        },
        {
            "current": 3250.056,
            "min": 1500.0,
            "max": 2450.0
        },
        {
            "current": 3249.52,
            "min": 1500.0,
            "max": 2450.0
        },
        {
            "current": 2596.695,
            "min": 1500.0,
            "max": 2450.0
        },
        {
            "current": 2592.667,
            "min": 1500.0,
            "max": 2450.0
        },
        {
            "current": 2594.939,
            "min": 1500.0,
            "max": 2450.0
        },
        {
            "current": 2596.542,
            "min": 1500.0,
            "max": 2450.0
        },
        {
            "current": 3249.421,
            "min": 1500.0,
            "max": 2450.0
        },
        {
            "current": 2600.018,
            "min": 1500.0,
            "max": 2450.0
        },
        {
            "current": 3249.758,
            "min": 1500.0,
            "max": 2450.0
        },
        {
            "current": 3249.376,
            "min": 1500.0,
            "max": 2450.0
        },
        {
            "current": 2599.31,
            "min": 1500.0,
            "max": 2450.0
        },
        {
            "current": 2599.556,
            "min": 1500.0,
            "max": 2450.0
        },
        {
            "current": 2602.443,
            "min": 1500.0,
            "max": 2450.0
        },
        {
            "current": 3250.033,
            "min": 1500.0,
            "max": 2450.0
        },
        {
            "current": 2598.804,
            "min": 1500.0,
            "max": 2450.0
        },
        {
            "current": 2903.556,
            "min": 1500.0,
            "max": 2450.0
        },
        {
            "current": 2597.723,
            "min": 1500.0,
            "max": 2450.0
        },
        {
            "current": 3250.097,
            "min": 1500.0,
            "max": 2450.0
        },
        {
            "current": 2590.246,
            "min": 1500.0,
            "max": 2450.0
        },
        {
            "current": 3249.61,
            "min": 1500.0,
            "max": 2450.0
        },
        {
            "current": 2596.297,
            "min": 1500.0,
            "max": 2450.0
        },
        {
            "current": 2598.04,
            "min": 1500.0,
            "max": 2450.0
        },
        {
            "current": 2596.641,
            "min": 1500.0,
            "max": 2450.0
        },
        {
            "current": 3249.358,
            "min": 1500.0,
            "max": 2450.0
        }
    ],
    "disk": {
        "/": {
            "total": 3665.955093383789,
            "used": 2668.958637237549
        }
    },
    "gpu": "NVIDIA RTX A6000",
    "gpu_count": 4,
    "gpu_devices": [
        {
            "name": "NVIDIA RTX A6000",
            "memory_total": 51527024640
        },
        {
            "name": "NVIDIA RTX A6000",
            "memory_total": 51527024640
        },
        {
            "name": "NVIDIA RTX A6000",
            "memory_total": 51527024640
        },
        {
            "name": "NVIDIA RTX A6000",
            "memory_total": 51527024640
        }
    ],
    "memory": {
        "total": 1007.7300682067871
    }
}
